{"roommates":[{"id":"3eedc5","nombre":"Ernest Hunt","debe":0,"recibe":0,"total":0,"correo":"ernest.hunt@example.com"},{"id":"2b54a7","nombre":"Helin Høie","debe":0,"recibe":0,"total":0,"correo":"helin.hoie@example.com"},{"id":"767496","nombre":"Paul Kurtz","debe":0,"recibe":0,"total":0,"correo":"paul.kurtz@example.com"},{"id":"c2662b","nombre":"Elif Pierre","debe":0,"recibe":0,"total":0,"correo":"elif.pierre@example.com"},{"id":"e34008","nombre":"Alexis Andre","debe":0,"recibe":0,"total":0,"correo":"alexis.andre@example.com"},{"id":"d2376d","nombre":"Vårin Harila","debe":0,"recibe":0,"total":0,"correo":"varin.harila@example.com"},{"id":"c8212e","nombre":"Danny Young","debe":0,"recibe":0,"total":0,"correo":"danny.young@example.com"},{"id":"c31731","nombre":"Ivan Pieper","debe":0,"recibe":0,"total":0,"correo":"ivan.pieper@example.com"},{"id":"5cae70","nombre":"Afet Denkel","debe":0,"recibe":0,"total":0,"correo":"afet.denkel@example.com"}]}